LICENSE
MANIFEST.in
README.md
setup.py
demiurge/__init__.py
demiurge/demiurge.py
demiurge.egg-info/PKG-INFO
demiurge.egg-info/SOURCES.txt
demiurge.egg-info/dependency_links.txt
demiurge.egg-info/not-zip-safe
demiurge.egg-info/requires.txt
demiurge.egg-info/top_level.txt