Metadata-Version: 1.1
Name: demiurge
Version: 0.1
Summary: Scraping micro-framework based on pyquery.
Home-page: https://github.com/matiasb/demiurge
Author: Matias Bordese
Author-email: mbordese@gmail.com
License: BSD
Keywords: scraping pyquery framework scraper web data extraction
Platform: UNKNOWN
Classifier: Intended Audience :: Developers
Classifier: License :: OSI Approved :: BSD License
Classifier: Programming Language :: Python :: 2
Classifier: Programming Language :: Python :: 2.7
Classifier: Programming Language :: Python :: 3
Classifier: Programming Language :: Python :: 3.3
